{
  "location": {
    "type": "Point",
    "coordinates": [
      -121.4842,
      48.4636
    ]
  },
  "relativeLocation": {
    "type": "Feature",
    "geometry": {
      "type": "Point",
      "coordinates": [
        -121.437344,
        48.536031
      ]
    },
    "properties": {
      "city": "Marblemount",
      "state": "WA",
      "distance": {
        "unitCode": "wmoUnit:m",
        "value": 8762.7210443436
      },
      "bearing": {
        "unitCode": "wmoUnit:degree_(angle)",
        "value": 203
      }
    },
    "elevation": {
      "unitCode": "wmoUnit:m",
      "value": 448.9704
    }
  },
  "updated": null,
  "forecastGenerator": "BaselineForecastGenerator",
  "forecast": [
    {
      "number": 1,
      "name": "Tonight",
      "startTime": "2024-10-08T23:00:00-07:00",
      "endTime": "2024-10-09T06:00:00-07:00",
      "isDaytime": false,
      "temperature": 49,
      "temperatureUnit": "F",
      "temperatureTrend": "",
      "probabilityOfPrecipitation": {
        "unitCode": "wmoUnit:percent",
        "value": 50
      },
      "windSpeed": "5 mph",
      "windDirection": "SW",
      "icon": "https://api.weather.gov/icons/land/night/rain_showers,50/rain_showers,40?size=medium",
      "shortForecast": "Chance Rain Showers",
      "detailedForecast": "A chance of rain showers. Mostly cloudy. Low around 49, with temperatures rising to around 52 overnight. Southwest wind around 5 mph. Chance of precipitation is 50%. New rainfall amounts less than a tenth of an inch possible."
    },
    {
      "number": 2,
      "name": "Wednesday",
      "startTime": "2024-10-09T06:00:00-07:00",
      "endTime": "2024-10-09T18:00:00-07:00",
      "isDaytime": true,
      "temperature": 55,
      "temperatureUnit": "F",
      "temperatureTrend": "",
      "probabilityOfPrecipitation": {
        "unitCode": "wmoUnit:percent",
        "value": 30
      },
      "windSpeed": "6 mph",
      "windDirection": "WSW",
      "icon": "https://api.weather.gov/icons/land/day/rain_showers,20/rain_showers,30?size=medium",
      "shortForecast": "Chance Rain Showers",
      "detailedForecast": "A chance of rain showers. Partly sunny. High near 55, with temperatures falling to around 53 in the afternoon. West southwest wind around 6 mph. Chance of precipitation is 30%. New rainfall amounts less than a tenth of an inch possible."
    }
  ]
}
