{
  "location": {
    "type": "Point",
    "coordinates": [
      -121.4842,
      48.4636
    ]
  },
  "relativeLocation": {
    "type": "Feature",
    "geometry": {
      "type": "Point",
      "coordinates": [
        -121.437344,
        48.536031
      ]
    },
    "properties": {
      "city": "Marblemount",
      "state": "WA",
      "distance": {
        "unitCode": "wmoUnit:m",
        "value": 8762.7210443436
      },
      "bearing": {
        "unitCode": "wmoUnit:degree_(angle)",
        "value": 203
      }
    },
    "elevation": {
      "unitCode": "wmoUnit:m",
      "value": 448.9704
    }
  },
  "updated": "2024-03-18T04:40:28+00:00",
  "forecastGenerator": "BaselineForecastGenerator",
  "forecast": [
    {
      "number": 1,
      "name": "Tonight",
      "startTime": "2024-03-17T23:00:00-07:00",
      "endTime": "2024-03-18T06:00:00-07:00",
      "isDaytime": false,
      "temperature": 49,
      "temperatureUnit": "F",
      "temperatureTrend": null,
      "probabilityOfPrecipitation": {
        "unitCode": "wmoUnit:percent",
        "value": null
      },
      "dewpoint": {
        "unitCode": "wmoUnit:degC",
        "value": 4.444444444444445
      },
      "relativeHumidity": {
        "unitCode": "wmoUnit:percent",
        "value": 63
      },
      "windSpeed": "6 mph",
      "windDirection": "ENE",
      "icon": "https://api.weather.gov/icons/land/night/few?size=medium",
      "shortForecast": "Mostly Clear",
      "detailedForecast": "Mostly clear, with a low around 49. East northeast wind around 6 mph."
    },
    {
      "number": 2,
      "name": "Monday",
      "startTime": "2024-03-18T06:00:00-07:00",
      "endTime": "2024-03-18T18:00:00-07:00",
      "isDaytime": true,
      "temperature": 68,
      "temperatureUnit": "F",
      "temperatureTrend": "falling",
      "probabilityOfPrecipitation": {
        "unitCode": "wmoUnit:percent",
        "value": null
      },
      "dewpoint": {
        "unitCode": "wmoUnit:degC",
        "value": 7.777777777777778
      },
      "relativeHumidity": {
        "unitCode": "wmoUnit:percent",
        "value": 63
      },
      "windSpeed": "2 to 7 mph",
      "windDirection": "WNW",
      "icon": "https://api.weather.gov/icons/land/day/few?size=medium",
      "shortForecast": "Sunny",
      "detailedForecast": "Sunny. High near 68, with temperatures falling to around 66 in the afternoon. West northwest wind 2 to 7 mph."
    }
  ]
}
