{
  "location": {
    "type": "Point",
    "coordinates": [
      -121.4842,
      48.4636
    ]
  },
  "relativeLocation": {
    "type": "Feature",
    "geometry": {
      "type": "Point",
      "coordinates": [
        -121.437344,
        48.536031
      ]
    },
    "properties": {
      "city": "Marblemount",
      "state": "WA",
      "distance": {
        "unitCode": "wmoUnit:m",
        "value": 8762.7210443436
      },
      "bearing": {
        "unitCode": "wmoUnit:degree_(angle)",
        "value": 203
      }
    },
    "elevation": {
      "unitCode": "wmoUnit:m",
      "value": 448.9704
    }
  },
  "updated": null,
  "forecastGenerator": "BaselineForecastGenerator",
  "forecast": [
    {
      "number": 1,
      "name": "Tonight",
      "startTime": "2024-08-09T23:00:00-07:00",
      "endTime": "2024-08-10T06:00:00-07:00",
      "isDaytime": false,
      "temperature": 64,
      "temperatureUnit": "F",
      "temperatureTrend": "",
      "probabilityOfPrecipitation": {
        "unitCode": "wmoUnit:percent",
        "value": null
      },
      "windSpeed": "3 mph",
      "windDirection": "ESE",
      "icon": "https://api.weather.gov/icons/land/night/haze?size=medium",
      "shortForecast": "Haze",
      "detailedForecast": "Haze before 5am. Clear, with a low around 64. East southeast wind around 3 mph."
    },
    {
      "number": 2,
      "name": "Saturday",
      "startTime": "2024-08-10T06:00:00-07:00",
      "endTime": "2024-08-10T18:00:00-07:00",
      "isDaytime": true,
      "temperature": 79,
      "temperatureUnit": "F",
      "temperatureTrend": "",
      "probabilityOfPrecipitation": {
        "unitCode": "wmoUnit:percent",
        "value": null
      },
      "windSpeed": "1 to 7 mph",
      "windDirection": "WSW",
      "icon": "https://api.weather.gov/icons/land/day/few?size=medium",
      "shortForecast": "Sunny",
      "detailedForecast": "Sunny, with a high near 79. West southwest wind 1 to 7 mph."
    }
  ]
}
